django_utils/__init__.py
django_utils/exceptions.py
django_utils/fields.py
django_utils/filters.py
django_utils/mock_request.py
django_utils/pagination.py
django_utils/utils.py
django_utils/views.py
django_utils/migrations/__init__.py
ws_cache/__init__.py
ws_cache/consumers.py
ws_cache/middleware.py
ws_cache/models.py
ws_cache/serializers.py
ws_cache/urls.py
ws_cache/views.py
django_ws_cache-1.0.2.dist-info/METADATA
django_ws_cache-1.0.2.dist-info/WHEEL
django_ws_cache-1.0.2.dist-info/top_level.txt
django_ws_cache-1.0.2.dist-info/RECORD
